{
  "Purchasable": true,
  "Cost": 19,
  "Data": {
    "Type": "InventoryItem",
    "Version": "1.0.0",
    "Rarity": "None",
    "Id": "87d0851b-c7f3-4df0-b214-6280ecf788f6",
    "Amount": 5
  },
  "Title": "Mob XP Boost II",
  "Description": "Collecting mobs from the map has never been more fun. XP galore!",
  "ThumbnailImageId": null,
  "CreationDate": "2020-02-25T23:06:00.875Z",
  "LastModifiedDate": "2021-01-05T17:13:13.371Z",
  "StartDate": "2019-10-14T17:00:00Z",
  "Id": "98c03065-5271-4303-933a-0643af1d1e41",
  "FriendlyId": null,
  "SourceEntityId": "B63A0803D3653643",
  "CreatorEntityId": "3B1B443CE3FD8EBA",
  "Tags": [
    "Boosts",
    "87d0851b-c7f3-4df0-b214-6280ecf788f6",
    "98c03065-5271-4303-933a-0643af1d1e41",
    "earth_discount"
  ],
  "Keywords": {},
  "Contents": [],
  "ItemReferences": [
    {
      "Id": "e313b9a4-f321-4d8c-acf2-1c5e0c70dbdc",
      "Amount": 5
    }
  ],
  "TitleTranslations": {
    "bg-BG": "Бонус към точките опит за моб II",
    "cs-CZ": "Vylepšení zkušeností za stvoření II",
    "da-DK": "XP-boost for væsener II",
    "de-DE": "Kreaturen-EP-Boost II",
    "el-GR": "Ενίσχυση πόντων εμπειρίας από πλάσματα II",
    "en-GB": "Mob XP Boost II",
    "es-ES": "Potenciador de EXP de criaturas II",
    "es-MX": "Mejora de EXP de criatura II",
    "fi-FI": "Olioiden XP-tehostus II",
    "fr-CA": "Amélioration d'EXP de créature\u00A0II",
    "fr-FR": "Amélioration d'XP (créatures)\u00A0II",
    "hu-HU": "Mob-TP erősítő II",
    "id-ID": "Pemacu XP Mob II",
    "it-IT": "XP creatura potenziati II",
    "ja-JP": "モブ XP ブースト II",
    "ko-KR": "몹 경험치 부스트 II",
    "nb-NO": "Vesen-XP-boost II",
    "nl-NL": "Mob-XP-boost II",
    "pl-PL": "Więcej doświadczenia z mobów II",
    "pt-BR": "Bônus de XP de Criaturas II",
    "pt-PT": "Aumento de XP de Criatura II",
    "ru-RU": "Увеличение опыта за мобов II",
    "sk-SK": "Zlepšenie skúseností za tvory II",
    "sv-SE": "XP-boost (varelser) II",
    "tr-TR": "Yaratık XP Artırıcı II",
    "uk-UA": "Збільшення досвіду за мобів II",
    "zh-CN": "生物经验增强 II",
    "zh-TW": "生物經驗值提升 II"
  },
  "DescriptionTranslations": {
    "bg-BG": "Събирането на мобове от картата никога не е било по-забавно. Изобилие от точки опит!",
    "cs-CZ": "Sbírání stvoření z mapy ještě nikdy nebyla taková zábava. Hromady zkušeností!",
    "da-DK": "Jagt på væsner har aldrig været sjovere. XP i hobetal!",
    "de-DE": "Kreaturen auf der Karte sammeln war noch nie so spaßig. EP bis zum Umfallen!",
    "el-GR": "Η συλλογή πλασμάτων από τον χάρτη ποτέ δεν ήταν πιο διασκεδαστική. Πληθώρα πόντων εμπειρίας!",
    "en-GB": "Collecting mobs from the map has never been more fun. XP galore!",
    "es-ES": "Recoger criaturas del mapa nunca ha sido tan divertido. ¡EXP a gogó!",
    "es-MX": "Recolectar criaturas del mapa es más divertido que nunca. ¡EXP a montones!",
    "fi-FI": "Olioiden kerääminen kartalta ei ole koskaan ollut hauskempaa. XP:tä kehiin!",
    "fr-CA": "La collecte de créatures de la carte n'aura jamais été aussi amusante. EXP en abondance!",
    "fr-FR": "Obtenir des créatures sur la carte n'a jamais été aussi amusant. Des tonnes d'XP\u00A0!",
    "hu-HU": "Mobok gyűjtése a térképről soha nem volt még ennyire szórakoztató. TP özön!",
    "id-ID": "Mengumpulkan mob dari peta tak pernah seseru ini. Pesta XP!",
    "it-IT": "Raccogliere creature dalla mappa non è mai stato così divertente. PE a volontà!",
    "ja-JP": "地図でモブを拾うのがこんなに楽しいなんて。XP がモリモリ入ります!",
    "ko-KR": "지도에서 몹을 몰고 다니는 게 이렇게 재밌던 적은 없었습니다. 경험치도 풍성합니다!",
    "nb-NO": "Det har aldri vært morsommere å samle vesener fra kartet. XP i massevis!",
    "nl-NL": "Het verzamelen van mobs was nog nooit zo leuk. XP in overvloed!",
    "pl-PL": "Zbieranie mobów na mapie jeszcze nigdy nie dawało tak dużo frajdy. Tyle PD, że hej!",
    "pt-BR": "Coletar criaturas no mapa nunca foi tão divertido. Muito XP!",
    "pt-PT": "Recolher criaturas do mapa nunca foi tão divertido. É a loucura do XP!",
    "ru-RU": "Собирать мобов еще никогда не было так весело. Опыта хоть отбавляй!",
    "sk-SK": "Zbieranie tvorov z mapy nikdy nebola väčšia zábava. Prináša množstvo skúseností.",
    "sv-SE": "Det har aldrig varit roligare att samla varelser på kartan. Vilken XP-fest!",
    "tr-TR": "Haritadan yaratık toplamak hiç bu kadar eğlenceli olmamıştı. XP bolluğu!",
    "uk-UA": "Збирати мобів на карті ще ніколи не було так весело. Рости, досвіде, рости!",
    "zh-CN": "从地图上收集生物变得前所未有地有趣。经验大爆发!",
    "zh-TW": "在地圖上收集生物從未如此有趣。大量經驗值!"
  }
}